{
  "id": "",
  "name": "",
  "font_family": "iconfont",
  "css_prefix_text": "icon-",
  "description": "",
  "glyphs": [
    {
      "icon_id": "20416227",
      "name": "宠物玩具",
      "font_class": "chongwuwanju",
      "unicode": "ed06",
      "unicode_decimal": 60678
    },
    {
      "icon_id": "20416228",
      "name": "狗狗出售",
      "font_class": "gougouchushou",
      "unicode": "ed07",
      "unicode_decimal": 60679
    },
    {
      "icon_id": "20416232",
      "name": "项圈用品",
      "font_class": "xiangquanyongpin",
      "unicode": "ed09",
      "unicode_decimal": 60681
    },
    {
      "icon_id": "20416233",
      "name": "外出箱包",
      "font_class": "waichuxiangbao",
      "unicode": "ed0a",
      "unicode_decimal": 60682
    },
    {
      "icon_id": "20416234",
      "name": "猫猫出售",
      "font_class": "maomaochushou",
      "unicode": "ed0b",
      "unicode_decimal": 60683
    },
    {
      "icon_id": "20416235",
      "name": "宠物洗浴",
      "font_class": "chongwuxiyu",
      "unicode": "ed0c",
      "unicode_decimal": 60684
    }
  ]
}
